aigens/__init__.py
aigens/blog/__init__.py
aigens/blog/ideas.py
aigens/blog/outline.py
aigens-0.3.dist-info/LICENSE.rst
aigens-0.3.dist-info/METADATA
aigens-0.3.dist-info/WHEEL
aigens-0.3.dist-info/top_level.txt
aigens-0.3.dist-info/RECORD
