Metadata-Version: 2.1
Name: aigens
Version: 0.3
Summary: AI Generator helpers using RapidAPI
Home-page: https://bitbucket.org/trycrimegroup/aigens/
Author: TryCrime
Author-email: lol@trycri.me
License: MIT
Keywords: rapidapi text generation
Platform: UNKNOWN
License-File: LICENSE.rst
Requires-Dist: requests
